{"props":{"pageProps":{"profile":{"description":"Alexandria Real Estate Equities, Inc. (NYSE:ARE), an S\u0026P 500\u003csup\u003e®\u003c/sup\u003e urban office real estate investment trust (\"REIT\"), is the first, longest-tenured, and pioneering owner, operator, and developer uniquely focused on collaborative life science, technology, and agtech campuses in AAA innovation cluster locations, with a total market capitalization of $31.9 billion as of December 31, 2020, and an asset base in North America of 49.7 million square feet (\"SF\"). The asset base in North America includes 31.9 million RSF of operating properties and 3.3 million RSF of Class A properties undergoing construction, 7.1 million RSF of near-term and intermediate-term development and redevelopment projects, and 7.4 million SF of future development projects. Founded in 1994, Alexandria pioneered this niche and has since established a significant market presence in key locations, including Greater Boston, San Francisco, New York City, San Diego, Seattle, Maryland, and Research Triangle. Alexandria has a longstanding and proven track record of developing Class A properties clustered in urban life science, technology, and agtech campuses that provide our innovative tenants with highly dynamic and collaborative environments that enhance their ability to successfully recruit and retain world-class talent and inspire productivity, efficiency, creativity, and success. Alexandria also provides strategic capital to transformative life science, technology, and agtech companies through our venture capital platform. We believe our unique business model and diligent underwriting ensure a high-quality and diverse tenant base that results in higher occupancy levels, longer lease terms, higher rental income, higher returns, and greater long-term asset value.","industry":"REIT—Office","symbol":"ARE","search":["a","ar","are","al","ale","alex","alexa","alexan","alexand","alexandr","alexandri","alexandria","alexandria ","alexandria r","alexandria re","alexandria rea","alexandria real","alexandria real ","alexandria real e","alexandria real es","alexandria real est","alexandria real esta","alexandria real estat","alexandria real estate","alexandria real estate ","alexandria real estate e","alexandria real estate eq","alexandria real estate equ","alexandria real estate equi","alexandria real estate equit","alexandria real estate equiti","alexandria real estate equitie","alexandria real estate equities","alexandria real estate equities,","alexandria real estate equities, ","alexandria real estate equities, i","alexandria real estate equities, in","alexandria real estate equities, inc","alexandria real estate equities, inc."],"ipoDate":"1997-05-28","website":"https://www.are.com","name":"Alexandria Real Estate Equities, Inc.","exchangeShort":"NYSE","isStatic":true,"sector":"Real Estate","currency":"USD"}},"__N_SSG":true},"page":"/quote/[symbol]","query":{"symbol":"ARE"},"buildId":"Njk4sJo_1dBWR55wHuASm","isFallback":false,"gsp":true,"scriptLoader":[]}