{"props":{"pageProps":{"profile":{"isStatic":true,"name":"Welltower Inc.","description":"Welltower Inc. (NYSE:WELL), an S\u0026P 500 company headquartered in Toledo, Ohio, is driving the transformation of health care infrastructure. The Company invests with leading seniors housing operators, post-acute providers and health systems to fund the real estate infrastructure needed to scale innovative care delivery models and improve people's wellness and overall health care experience. Welltower™, a real estate investment trust (\"REIT\"), owns interests in properties concentrated in major, high-growth markets in the United States, Canada and the United Kingdom, consisting of seniors housing and post-acute communities and outpatient medical properties.","industry":"REIT—Healthcare Facilities","search":["w","we","wel","well","wellt","wellto","welltow","welltowe","welltower","welltower ","welltower i","welltower in","welltower inc","welltower inc."],"currency":"USD","website":"https://www.welltower.com","ipoDate":"1992-12-17","sector":"Real Estate","exchangeShort":"NYSE","symbol":"WELL"}},"__N_SSG":true},"page":"/quote/[symbol]","query":{"symbol":"WELL"},"buildId":"Njk4sJo_1dBWR55wHuASm","isFallback":false,"gsp":true,"scriptLoader":[]}